pyuninstaller/__init__.py
pyuninstaller/__main__.py
pyuninstaller-0.0.1.dist-info/entry_points.txt
pyuninstaller-0.0.1.dist-info/LICENSE
pyuninstaller-0.0.1.dist-info/WHEEL
pyuninstaller-0.0.1.dist-info/METADATA
pyuninstaller-0.0.1.dist-info/RECORD
