Metadata-Version: 2.1
Name: pyuninstaller
Version: 0.0.1
Summary: Decompile what pyinstaller creates.
Home-page: https://github.com/supakeen/pyuninstaller
License: MIT
Keywords: pastebin
Author: supakeen
Author-email: cmdr@supakeen.com
Requires-Python: >=3.6,<4
Classifier: License :: OSI Approved :: MIT License
Classifier: Programming Language :: Python
Classifier: Programming Language :: Python :: 3
Classifier: Programming Language :: Python :: 3.6
Classifier: Programming Language :: Python :: 3.7
Classifier: Programming Language :: Python :: 3.8
Requires-Dist: click (>=7.0,<8.0)
Requires-Dist: pyinstaller (>=3.6,<4.0)
Requires-Dist: uncompyle6 (>=3.6.6,<4.0.0)
Project-URL: Repository, https://github.com/supakeen/pyuninstaller
